Workbook

Sheet Report
A1: Which jobs actually make money?
A2: Sample Electrical & Air Pty Ltd · SAMPLE DATA (invented) · The Fourth Sheet
A3: Period: October 2025 · Data status: Sep 2025 locked · Oct 2025 locked · Oct 2026 incomplete (data retrieved 2pm, Tue 6 Oct 2026)
A5: Every job's gross margin: revenue less materials, subcontractors and technician time at $68 an hour (fully loaded: wages and all on-costs). Pick a type of job and every number, chart and note on the page follows it.
A7: Gross margin, not profit
A8: Gross margin is not profit. Job gross margin = revenue less materials, subcontractors and technician time charged to the job at $68 an hour (wages and all on-costs). Not included: technician time not charged to any job (travel, training, waiting), and overheads (office wages, marketing, vehicles, rent, insurance, IT, depreciation, interest). Profit is what's left after those. Wages always include all on-costs: super, payroll tax, workers' compensation insurance and leave.
A10: From gross margin to profit
A11: October's jobs made $49,446 gross margin (38.4%). Technician time not charged to jobs took $9,638 and overheads $57,980, leaving ($18,172) profit before tax ((14.1%) of revenue). To cover overheads, jobs need a 52.5% gross margin on average. (Workings sheet: "From gross margin to profit".)
A13: Type of job: All jobs
A14: Headline number | B14: Value | C14: Compared with
A15: Job gross margin, October · All jobs | B15: =Workings!B28 | C15: target 35.0%
A16: Job gross margin, September · All jobs | B16: =Workings!B37 | C16: target 35.0%
A17: Gross margin jobs need to break even | B17: =Workings!B53 | C17: covers overheads and time not charged (October)
A19: Job gross margin by type of job, October 2025
B20: Gross margin % | C20: Gross margin $
A21: Maintenance contracts | B21: =Workings!B63 | C21: =Workings!B62
A22: Installations | B22: =Workings!B72 | C22: =Workings!B71
A23: Call-outs and repairs | B23: =Workings!B81 | C23: =Workings!B80
A25: What it shows
A26: In October maintenance contracts made a 59.5% job gross margin, installations made a 26.1% job gross margin, call-outs and repairs made a 43.3% job gross margin (technician time at $68 an hour, wages and all on-costs). Jobs need 52.5% just to cover overheads.
A28: What you'd do about it
A29: Installations: 26.1% gross margin, 8.9 points under the 35.0% target: about $6,268 on $70,800 of revenue in October. It's below the 52.5% needed to cover overheads, too. Maintenance contracts: 59.5% gross margin, 24.5 points over the 35.0% target ($8,754 ahead on $35,800 in October).
A31: Type of job: Maintenance contracts
A32: Headline number | B32: Value | C32: Compared with
A33: Job gross margin, October · Maintenance contracts | B33: =Workings!B90 | C33: target 35.0%
A34: Job gross margin, September · Maintenance contracts | B34: =Workings!B99 | C34: target 35.0%
A35: Gross margin jobs need to break even | B35: =Workings!B115 | C35: covers overheads and time not charged (October)
A37: Job gross margin on each maintenance contract, October 2025
B38: Gross margin % | C38: Gross margin $
A39: Wynnum medical centre | B39: =Workings!B129 | C39: =Workings!B128
A40: Southbank cafe group | B40: =Workings!B142 | C40: =Workings!B141
A41: Ashgrove aged care | B41: =Workings!B155 | C41: =Workings!B154
A42: Fortitude Valley hotel | B42: =Workings!B168 | C42: =Workings!B167
A43: Riverside Apartments (strata) | B43: =Workings!B181 | C43: =Workings!B180
A44: Newstead gym | B44: =Workings!B194 | C44: =Workings!B193
A45: Chermside retail centre | B45: =Workings!B207 | C45: =Workings!B206
A46: Milton office tower | B46: =Workings!B220 | C46: =Workings!B219
A47: Bulimba school | B47: =Workings!B233 | C47: =Workings!B232
A48: West End brewery | B48: =Workings!B246 | C48: =Workings!B245
A49: Rocklea factory | B49: =Workings!B259 | C49: =Workings!B258
A50: Kangaroo Point townhouses | B50: =Workings!B272 | C50: =Workings!B271
A52: What it shows
A53: All 12 contracts made more than the 35.0% job gross margin target. The thinnest was Kangaroo Point townhouses at 58.2% job gross margin: 14.0 h of technician time on a $2,400 monthly fee.
A55: What you'd do about it
A56: The thinnest, Kangaroo Point townhouses: 58.2% gross margin, 23.3 points over the 35.0% target ($558 ahead on $2,400 in October). All maintenance contracts: 59.5% gross margin, 24.5 points over the 35.0% target ($8,754 ahead on $35,800 in October).
A58: Type of job: Installations
A59: Headline number | B59: Value | C59: Compared with
A60: Job gross margin, October · Installations | B60: =Workings!B281 | C60: target 35.0%
A61: Job gross margin, September · Installations | B61: =Workings!B290 | C61: target 35.0%
A62: Gross margin jobs need to break even | B62: =Workings!B306 | C62: covers overheads and time not charged (October)
A64: Job gross margin on each installation invoiced in October 2025
B65: Gross margin % | C65: Gross margin $
A66: Aspley cafe data cabling | B66: =Workings!B320 | C66: =Workings!B319
A67: Coorparoo shop air-con install | B67: =Workings!B333 | C67: =Workings!B332
A68: Salisbury shop solar and battery | B68: =Workings!B346 | C68: =Workings!B345
A70: What it shows
A71: 2 of the 3 installation jobs invoiced in October made less than the 35.0% job gross margin target. The Salisbury shop solar and battery made a 17.3% job gross margin: 120.0 h of technician time ($8,160) and $3,900 of subcontractors on a $35,500 job. Jobs need 52.5% gross margin just to cover overheads.
A73: What you'd do about it
A74: 2 installations under the 35.0% target, worth about $6,744 between them on $54,000 of revenue. The biggest gap, Salisbury shop solar and battery: 17.3% gross margin, 17.7 points under the 35.0% target: about $6,285 on $35,500 of revenue in October. It's below the 52.5% needed to cover overheads, too.
A76: Type of job: Call-outs and repairs
A77: Headline number | B77: Value | C77: Compared with
A78: Job gross margin, October · Call-outs and repairs | B78: =Workings!B355 | C78: target 35.0%
A79: Job gross margin, September · Call-outs and repairs | B79: =Workings!B364 | C79: target 35.0%
A80: Gross margin jobs need to break even | B80: =Workings!B380 | C80: covers overheads and time not charged (October)
A81: Technician time charged, October | B81: =Workings!B393 | C81: 67.3% of call-out revenue
A82: Materials charged, October | B82: =Workings!B405 | C82: $5,610 at cost, plus 30%
A84: Job gross margin on call-outs by length, October 2025
B85: Gross margin % | C85: Gross margin $
A86: 1-hour call-outs (7) | B86: =Workings!B418 | C86: =Workings!B417
A87: 1.5-hour call-outs (3) | B87: =Workings!B431 | C87: =Workings!B430
A88: 2-hour call-outs (9) | B88: =Workings!B444 | C88: =Workings!B443
A89: 2.5-hour call-outs (8) | B89: =Workings!B457 | C89: =Workings!B456
A90: 3-hour call-outs (10) | B90: =Workings!B470 | C90: =Workings!B469
A91: 4-hour call-outs (6) | B91: =Workings!B483 | C91: =Workings!B482
A93: What it shows
A94: 43 call-outs in October billed $15,005 of technician time and $7,293 of materials ($5,610 at cost plus 30%), and made a 43.3% job gross margin between them. Gross margins run from 37.8% to 45.9% by length: the hourly rate covers technician time comfortably, so the gross margin mostly moves with how much material goes on the van.
A96: What you'd do about it
A97: All call-outs: 43.3% gross margin, 8.3 points over the 35.0% target ($1,846 ahead on $22,298 in October).
A99: Every type of job at once
A100: Job gross margin by month: every month is on the Data sheet.

Sheet Workings
A1: How each number is worked out
A2: Sample Electrical & Air Pty Ltd · SAMPLE DATA (invented) · The Fourth Sheet
A3: Period: October 2025 · Data status: Sep 2025 locked · Oct 2025 locked · Oct 2026 incomplete (data retrieved 2pm, Tue 6 Oct 2026)
A5: From gross margin to profit, October 2025
A6: Gross margin on the work − time not charged − overheads = profit before tax
B7: Oct 2025
A8: Gross margin on jobs | B8: 49446
A9: Technician wages and on-costs | B9: 46800
A10: Technician time charged to jobs (at cost) | B10: 37162
A11: Technician time not charged to jobs | B11: =B9-B10
A12: Gross profit (the P&L) | B12: =B8-B11
A13: Overheads (operating expenses, depreciation, interest) | B13: 57980
A14: Profit before tax (the P&L) | B14: =B12-B13
A15: Revenue | B15: 128898
A16: Gross margin on jobs, % | B16: =B8/B15
A17: Profit before tax, % of revenue | B17: =B14/B15
A18: Gross margin jobs need just to cover overheads and time not charged | B18: =(B11+B13)/B15
A19: Ties to the October 2025 P&L (locked). Wages always include all on-costs: super, payroll tax, workers' compensation insurance and leave.
A22: All lines: gross margin, October and September
A23: Revenue less direct cost, over revenue. Before overheads.
B24: Oct 25 | C24: Sep 25
A25: Revenue | B25: 128898 | C25: 128255
A26: Direct cost | B26: 79452 | C26: 80054
A27: Gross margin | B27: =B25-B26 | C27: =C25-C26
A28: Gross margin % | B28: =B27/B25 | C28: =C27/C25
A31: All lines: gross margin, October and September
A32: Revenue less direct cost, over revenue. Before overheads.
B33: Oct 25 | C33: Sep 25
A34: Revenue | B34: 128898 | C34: 128255
A35: Direct cost | B35: 79452 | C35: 80054
A36: Gross margin | B36: =B34-B35 | C36: =C34-C35
A37: Gross margin % | B37: =B36/B34 | C37: =C36/C34
A40: From gross margin to profit, October 2025
A41: Gross margin on the work − time not charged − overheads = profit before tax
B42: Oct 2025
A43: Gross margin on jobs | B43: 49446
A44: Technician wages and on-costs | B44: 46800
A45: Technician time charged to jobs (at cost) | B45: 37162
A46: Technician time not charged to jobs | B46: =B44-B45
A47: Gross profit (the P&L) | B47: =B43-B46
A48: Overheads (operating expenses, depreciation, interest) | B48: 57980
A49: Profit before tax (the P&L) | B49: =B47-B48
A50: Revenue | B50: 128898
A51: Gross margin on jobs, % | B51: =B43/B50
A52: Profit before tax, % of revenue | B52: =B49/B50
A53: Gross margin jobs need just to cover overheads and time not charged | B53: =(B46+B48)/B50
A54: Ties to the October 2025 P&L (locked). Wages always include all on-costs: super, payroll tax, workers' compensation insurance and leave.
A57: Maintenance contracts, October
A58: Revenue less direct cost (materials, subcontractors, technician time at cost)
B59: Oct 2025
A60: Revenue | B60: 35800
A61: Direct cost | B61: 14516
A62: Gross margin | B62: =B60-B61
A63: Gross margin % | B63: =B62/B60
A66: Installations, October
A67: Revenue less direct cost (materials, subcontractors, technician time at cost)
B68: Oct 2025
A69: Revenue | B69: 70800
A70: Direct cost | B70: 52288
A71: Gross margin | B71: =B69-B70
A72: Gross margin % | B72: =B71/B69
A75: Call-outs and repairs, October
A76: Revenue less direct cost (materials, subcontractors, technician time at cost)
B77: Oct 2025
A78: Revenue | B78: 22298
A79: Direct cost | B79: 12648
A80: Gross margin | B80: =B78-B79
A81: Gross margin % | B81: =B80/B78
A84: Maintenance contracts: gross margin, October and September
A85: Revenue less direct cost, over revenue. Before overheads.
B86: Oct 25 | C86: Sep 25
A87: Revenue | B87: 35800 | C87: 33200
A88: Direct cost | B88: 14516 | C88: 13446
A89: Gross margin | B89: =B87-B88 | C89: =C87-C88
A90: Gross margin % | B90: =B89/B87 | C90: =C89/C87
A93: Maintenance contracts: gross margin, October and September
A94: Revenue less direct cost, over revenue. Before overheads.
B95: Oct 25 | C95: Sep 25
A96: Revenue | B96: 35800 | C96: 33200
A97: Direct cost | B97: 14516 | C97: 13446
A98: Gross margin | B98: =B96-B97 | C98: =C96-C97
A99: Gross margin % | B99: =B98/B96 | C99: =C98/C96
A102: From gross margin to profit, October 2025
A103: Gross margin on the work − time not charged − overheads = profit before tax
B104: Oct 2025
A105: Gross margin on jobs | B105: 49446
A106: Technician wages and on-costs | B106: 46800
A107: Technician time charged to jobs (at cost) | B107: 37162
A108: Technician time not charged to jobs | B108: =B106-B107
A109: Gross profit (the P&L) | B109: =B105-B108
A110: Overheads (operating expenses, depreciation, interest) | B110: 57980
A111: Profit before tax (the P&L) | B111: =B109-B110
A112: Revenue | B112: 128898
A113: Gross margin on jobs, % | B113: =B105/B112
A114: Profit before tax, % of revenue | B114: =B111/B112
A115: Gross margin jobs need just to cover overheads and time not charged | B115: =(B108+B110)/B112
A116: Ties to the October 2025 P&L (locked). Wages always include all on-costs: super, payroll tax, workers' compensation insurance and leave.
A119: Wynnum medical centre
A120: Job gross margin ÷ revenue for this job (before overheads)
B121: This job
...

Sheet Data
A1: Data
A2: Sample Electrical & Air Pty Ltd · SAMPLE DATA (invented) · The Fourth Sheet
A3: Period: October 2025 · Data status: Sep 2025 locked · Oct 2025 locked · Oct 2026 incomplete (data retrieved 2pm, Tue 6 Oct 2026)
A5: Line | B5: Month | C5: Status | D5: Revenue | E5: Direct cost | F5: Gross margin | G5: Gross margin %
A6: All | B6: Oct 24 | C6: Locked | D6: 171009 | E6: 114334 | F6: =D6-E6 | G6: =IF(D6=0,"",F6/D6)
A7: All | B7: Nov 24 | C7: Locked | D7: 179474 | E7: 113016 | F7: =D7-E7 | G7: =IF(D7=0,"",F7/D7)
A8: All | B8: Dec 24 | C8: Locked | D8: 143156 | E8: 85316 | F8: =D8-E8 | G8: =IF(D8=0,"",F8/D8)
A9: All | B9: Jan 25 | C9: Locked | D9: 140909 | E9: 80742 | F9: =D9-E9 | G9: =IF(D9=0,"",F9/D9)
A10: All | B10: Feb 25 | C10: Locked | D10: 160943 | E10: 102348 | F10: =D10-E10 | G10: =IF(D10=0,"",F10/D10)
A11: All | B11: Mar 25 | C11: Locked | D11: 135082 | E11: 85752 | F11: =D11-E11 | G11: =IF(D11=0,"",F11/D11)
A12: All | B12: Apr 25 | C12: Locked | D12: 124705 | E12: 76808 | F12: =D12-E12 | G12: =IF(D12=0,"",F12/D12)
A13: All | B13: May 25 | C13: Locked | D13: 129816 | E13: 83700 | F13: =D13-E13 | G13: =IF(D13=0,"",F13/D13)
A14: All | B14: Jun 25 | C14: Locked | D14: 164113 | E14: 97584 | F14: =D14-E14 | G14: =IF(D14=0,"",F14/D14)
A15: All | B15: Jul 25 | C15: Locked | D15: 186760 | E15: 120326 | F15: =D15-E15 | G15: =IF(D15=0,"",F15/D15)
A16: All | B16: Aug 25 | C16: Locked | D16: 139164 | E16: 78258 | F16: =D16-E16 | G16: =IF(D16=0,"",F16/D16)
A17: All | B17: Sep 25 | C17: Locked | D17: 128255 | E17: 80054 | F17: =D17-E17 | G17: =IF(D17=0,"",F17/D17)
... A57: Call-outs and repairs | B57: Oct 25 | C57: Locked | D57: 22298 | E57: 12648 | F57: =D57-E57 | G57: =IF(D57=0,"",F57/D57)
